{
  "courses": [
    {
      "id": 1,
      "title": "Guitar Fundamentals",
      "slug": "guitar-fundamentals",
      "description": "Learn the basics of playing guitar with our comprehensive beginner's course.",
      "price": 99.99,
      "instructor": "John Doe",
      "isFeatured": true,
      "image": "/courses/guitar.jpg"
    },
    {
      "id": 2,
      "title": "Piano for Beginners",
      "slug": "piano-for-beginners",
      "description": "Start your musical journey with foundational piano skills taught by expert instructors.",
      "price": 109.99,
      "instructor": "Jane Smith",
      "isFeatured": false,
      "image": "/courses/piano.jpg"
    },
    {
      "id": 3,
      "title": "Advanced Vocal Techniques",
      "slug": "advanced-vocal-techniques",
      "description": "Enhance your singing with advanced vocal techniques for intermediate to advanced learners.",
      "price": 119.99,
      "instructor": "Emily Johnson",
      "isFeatured": true,
      "image": "/courses/vocalist.jpg"
    },
    {
      "id": 4,
      "title": "Drumming Mastery",
      "slug": "drumming-mastery",
      "description": "Master the drums with our comprehensive course covering all skill levels.",
      "price": 129.99,
      "instructor": "Mike Brown",
      "isFeatured": false,
      "image": "/courses/drumming.jpg"
    },
    {
      "id": 5,
      "title": "Jazz Improvisation",
      "slug": "jazz-improvisation",
      "description": "Learn the art of jazz improvisation with this course designed for all levels.",
      "price": 139.99,
      "instructor": "Chris Davis",
      "isFeatured": false,
      "image": "/courses/jazz.jpg"
    },
    {
      "id": 6,
      "title": "Music Production Fundamentals",
      "slug": "music-production-fundamentals",
      "description": "Dive into music production with this introductory course on the basics of sound engineering and mixing.",
      "price": 149.99,
      "instructor": "Alex Wilson",
      "isFeatured": true,
      "image": "/courses/music-prod.jpg"
    },
    {
      "id": 7,
      "title": "Songwriting Essentials",
      "slug": "songwriting-essentials",
      "description": "Learn the essentials of songwriting to express your musical creativity.",
      "price": 159.99,
      "instructor": "Samantha Miller",
      "isFeatured": false,
      "image": "/courses/song-writing.jpg"
    },
    {
      "id": 8,
      "title": "Electronic Music Production",
      "slug": "electronic-music-production",
      "description": "Create compelling electronic music with our course designed for beginners to advanced users.",
      "price": 169.99,
      "instructor": "Luke Harris",
      "isFeatured": true,
      "image": "/courses/music-prod.jpg"
    },
    {
      "id": 9,
      "title": "Classical Music History",
      "slug": "classical-music-history",
      "description": "Explore the rich history of classical music from its origins to the present day.",
      "price": 179.99,
      "instructor": "Grace Lee",
      "isFeatured": false,
      "image": "/courses/classical-music.jpg"
    },
    {
      "id": 10,
      "title": "Blues Guitar Techniques",
      "slug": "blues-guitar-techniques",
      "description": "Discover the techniques of blues guitar to add soul and depth to your playing.",
      "price": 189.99,
      "instructor": "Ethan Moore",
      "isFeatured": true,
      "image": "/courses/blues.jpg"
    },
    {
      "id": 11,
      "title": "Acoustic Guitar Techniques",
      "slug": "acoustic-guitar-techniques",
      "description": "Master the art of acoustic guitar with techniques for all levels of players.",
      "price": 95.99,
      "instructor": "David Hill",
      "isFeatured": false,
      "image": "https://images.unsplash.com/photo-1509316785284-1b4d58a00705?ixid=M3wxMjA3fDB8MHxwaG90by1wYWdlfHx8fGVufDB8fHx8&auto=format&fit=crop&w=800&q=60"
    },
    {
      "id": 12,
      "title": "Intermediate Piano Mastery",
      "slug": "intermediate-piano-mastery",
      "description": "Improve your piano skills with this course for intermediate players.",
      "price": 120.99,
      "instructor": "Emily Roberts",
      "isFeatured": false,
      "image": "https://images.unsplash.com/photo-1554469387-7aefa6c1f07f?ixid=M3wxMjA3fDB8MHxwaG90by1wYWdlfHx8fGVufDB8fHx8&auto=format&fit=crop&w=800&q=60"
    },
    {
      "id": 13,
      "title": "Vocal Warm-Ups and Techniques",
      "slug": "vocal-warm-ups-techniques",
      "description": "Perfect your voice with a focus on vocal warm-ups and control techniques.",
      "price": 130.99,
      "instructor": "Lily Carter",
      "isFeatured": true,
      "image": "https://images.unsplash.com/photo-1545460206-d0bff6a01246?ixid=M3wxMjA3fDB8MHxwaG90by1wYWdlfHx8fGVufDB8fHx8&auto=format&fit=crop&w=800&q=60"
    },
    {
      "id": 14,
      "title": "Percussion for Beginners",
      "slug": "percussion-for-beginners",
      "description": "Start your percussion journey with an in-depth introduction to rhythm and techniques.",
      "price": 110.99,
      "instructor": "George White",
      "isFeatured": false,
      "image": "https://images.unsplash.com/photo-1529630833835-48b2d2b3ff51?ixid=M3wxMjA3fDB8MHxwaG90by1wYWdlfHx8fGVufDB8fHx8&auto=format&fit=crop&w=800&q=60"
    },
    {
      "id": 15,
      "title": "Funk Bass Guitar",
      "slug": "funk-bass-guitar",
      "description": "Learn the groovy rhythms of funk bass guitar, perfect for intermediate players.",
      "price": 135.99,
      "instructor": "Steven Clark",
      "isFeatured": true,
      "image": "https://images.unsplash.com/photo-1592596511303-81573dfbf249?ixid=M3wxMjA3fDB8MHxwaG90by1wYWdlfHx8fGVufDB8fHx8&auto=format&fit=crop&w=800&q=60"
    },
    {
      "id": 16,
      "title": "Rock Band Essentials",
      "slug": "rock-band-essentials",
      "description": "Discover the essential skills needed to perform in a rock band, covering multiple instruments.",
      "price": 145.99,
      "instructor": "Jessica Turner",
      "isFeatured": false,
      "image": "https://images.unsplash.com/photo-1504384308090-c894fdcc538d?ixid=M3wxMjA3fDB8MHxwaG90by1wYWdlfHx8fGVufDB8fHx8&auto=format&fit=crop&w=800&q=60"
    },
    {
      "id": 17,
      "title": "Music Theory Made Easy",
      "slug": "music-theory-made-easy",
      "description": "Understand music theory with this comprehensive yet accessible course for all musicians.",
      "price": 105.99,
      "instructor": "Paul Brown",
      "isFeatured": true,
      "image": "https://images.unsplash.com/photo-1598387841175-6478e0cdb8b9?ixid=M3wxMjA3fDB8MHxwaG90by1wYWdlfHx8fGVufDB8fHx8&auto=format&fit=crop&w=800&q=60"
    },
    {
      "id": 18,
      "title": "Sound Design for Film",
      "slug": "sound-design-for-film",
      "description": "Create compelling soundscapes for film with this introductory sound design course.",
      "price": 155.99,
      "instructor": "Anna Mitchell",
      "isFeatured": true,
      "image": "https://images.unsplash.com/photo-1484863137850-59afcfe05386?ixid=M3wxMjA3fDB8MHxwaG90by1wYWdlfHx8fGVufDB8fHx8&auto=format&fit=crop&w=800&q=60"
    },
    {
      "id": 19,
      "title": "The Art of Music Mixing",
      "slug": "art-of-music-mixing",
      "description": "Learn the skills to professionally mix tracks for any genre of music.",
      "price": 165.99,
      "instructor": "Brian Martin",
      "isFeatured": false,
      "image": "https://images.unsplash.com/photo-1593642634315-48f5414c3ad9?ixid=M3wxMjA3fDB8MHxwaG90by1wYWdlfHx8fGVufDB8fHx8&auto=format&fit=crop&w=800&q=60"
    },
    {
      "id": 20,
      "title": "Latin Percussion Rhythms",
      "slug": "latin-percussion-rhythms",
      "description": "Explore the exciting world of Latin percussion with rhythms from around the globe.",
      "price": 175.99,
      "instructor": "Carlos Sanchez",
      "isFeatured": false,
      "image": "https://images.unsplash.com/photo-1565026185782-49e9f17a7ab7?ixid=M3wxMjA3fDB8MHxwaG90by1wYWdlfHx8fGVufDB8fHx8&auto=format&fit=crop&w=800&q=60"
    }
  ]
}
